albumsPicker/__init__.py
albumsPicker/album.py
albumsPicker/albums.json
albumsPicker/albums_picker.py
albumsPicker/qobuz_essential_discography.json
albums_picker-1.0.1.dist-info/LICENSE
albums_picker-1.0.1.dist-info/METADATA
albums_picker-1.0.1.dist-info/WHEEL
albums_picker-1.0.1.dist-info/entry_points.txt
albums_picker-1.0.1.dist-info/top_level.txt
albums_picker-1.0.1.dist-info/RECORD
