Metadata-Version: 2.1
Name: albums-picker
Version: 1.0.1
Summary: Picks a random album from 1001 Albums You Must Hear Before You Die
Author-email: Santiago Mondragon <santiago.mondragon224@gmail.com>
Project-URL: Homepage, https://github.com/santi224m/1001-albums-picker
Project-URL: Issues, https://github.com/santi224m/1001-albums-picker/issues
Classifier: Programming Language :: Python :: 3
Classifier: License :: OSI Approved :: MIT License
Classifier: Operating System :: OS Independent
Requires-Python: >=3.8
License-File: LICENSE
Requires-Dist: rich >=13.7.1
